mag_cal/__init__.py
mag_cal/axes.py
mag_cal/calibration.py
mag_cal/lstsq.py
mag_cal/nm.py
mag_cal/rbf.py
mag_cal/sensor.py
mag_cal/utils.py
circuitpython_mag_cal-1.4.1.dist-info/LICENSE
circuitpython_mag_cal-1.4.1.dist-info/METADATA
circuitpython_mag_cal-1.4.1.dist-info/WHEEL
circuitpython_mag_cal-1.4.1.dist-info/top_level.txt
circuitpython_mag_cal-1.4.1.dist-info/RECORD
