Metadata-Version: 2.1
Name: circuitpython-mag-cal
Version: 1.4.1
Summary: Calibrate magnetometer and accelerometer readings
Author-email: Adafruit Industries <circuitpython@adafruit.com>
License: MIT
Project-URL: Homepage, https://github.com/furbrain/CircuitPython_mag_cal
Keywords: adafruit,blinka,circuitpython,micropython,mag_cal,magnetometer,accelerometer,compass,calibrate,calibration,gravity,magnetism,magnetic
Classifier: Intended Audience :: Developers
Classifier: Topic :: Software Development :: Libraries
Classifier: Topic :: Software Development :: Embedded Systems
Classifier: Topic :: System :: Hardware
Classifier: License :: OSI Approved :: MIT License
Classifier: Programming Language :: Python :: 3
License-File: LICENSE
Requires-Dist: Adafruit-Blinka
Requires-Dist: numpy
Requires-Dist: scipy
Provides-Extra: optional
